damadara_xyz/__init__.py
damadara_xyz/main.py
damadara_xyz/configs/cleaning_config.yaml
damadara_xyz/configs/presentation_config.yaml
damadara_xyz/configs/semantic_config.yaml
damadara_xyz/detailed_cleaning/__init__.py
damadara_xyz/detailed_cleaning/consistency_checker.py
damadara_xyz/detailed_cleaning/logic_enforcer.py
damadara_xyz/detailed_cleaning/outlier_handler.py
damadara_xyz/detailed_cleaning/reference_validator.py
damadara_xyz/detailed_cleaning/semantic_summary.py
damadara_xyz/root_cleaning/__init__.py
damadara_xyz/root_cleaning/base_cleaner.py
damadara_xyz/root_cleaning/duplicates_handler.py
damadara_xyz/root_cleaning/missing_value_handler.py
damadara_xyz/root_cleaning/pipeline.py
damadara_xyz/root_cleaning/text_cleaner.py
damadara_xyz/root_cleaning/type_standardizer.py
damadara_xyz/root_cleaning/validator.py
damadara_xyz/superficial_cleaning/__init__.py
damadara_xyz/superficial_cleaning/beautifier.py
damadara_xyz/superficial_cleaning/column_formatter.py
damadara_xyz/superficial_cleaning/datetime_formatter.py
damadara_xyz/superficial_cleaning/label_standardizer.py
damadara_xyz/superficial_cleaning/metadata_generator.py
damadara_xyz/superficial_cleaning/numeric_formatter.py
damadara_xyz-0.1.1.dist-info/METADATA
damadara_xyz-0.1.1.dist-info/WHEEL
damadara_xyz-0.1.1.dist-info/entry_points.txt
damadara_xyz-0.1.1.dist-info/top_level.txt
damadara_xyz-0.1.1.dist-info/RECORD
