Metadata-Version: 2.4
Name: damadara_xyz
Version: 0.1.1
Summary: 3-Layer Data Cleaning Pipeline: L0 Basic, L1 Semantic, L2 Presentation
Author-email: Your Name <your.email@example.com>
License: MIT
Project-URL: Homepage, https://github.com/yourusername/damadara_xyz
Project-URL: Repository, https://github.com/yourusername/damadara_xyz
Requires-Python: >=3.8
Requires-Dist: pandas>=1.5.0
Requires-Dist: pyyaml>=6.0
Requires-Dist: numpy<2.0,>=1.21.0
Provides-Extra: dev
Requires-Dist: pytest; extra == "dev"
Requires-Dist: black; extra == "dev"
